obspec/__init__.py
obspec/_attributes.py
obspec/_copy.py
obspec/_delete.py
obspec/_get.py
obspec/_head.py
obspec/_list.py
obspec/_meta.py
obspec/_put.py
obspec/_rename.py
obspec/_version.py
obspec/exceptions.py
obspec/py.typed
obspec-0.1.0.dist-info/METADATA
obspec-0.1.0.dist-info/WHEEL
obspec-0.1.0.dist-info/licenses/LICENSE
obspec-0.1.0.dist-info/RECORD
