Metadata-Version: 2.4
Name: obspec
Version: 0.1.0
Summary: Object storage interface definitions for Python.
Project-URL: homepage, https://developmentseed.org/obspec/latest/
Project-URL: documentation, https://developmentseed.org/obspec/latest/
Project-URL: repository, https://github.com/developmentseed/obspec
Project-URL: issues, https://github.com/developmentseed/obspec/issues
Project-URL: changelog, https://github.com/developmentseed/obspec/blob/main/CHANGELOG.md
Author-email: Kyle Barron <kyle@developmentseed.org>
License-Expression: MIT
License-File: LICENSE
Classifier: Development Status :: 4 - Beta
Classifier: License :: OSI Approved :: MIT License
Classifier: Operating System :: OS Independent
Classifier: Programming Language :: Python :: 3
Classifier: Programming Language :: Python :: 3 :: Only
Requires-Python: >=3.9
Requires-Dist: typing-extensions; python_version < '3.12'
